observing_machine/__init__.py
observing_machine-0.0.1.dist-info/LICENSE
observing_machine-0.0.1.dist-info/METADATA
observing_machine-0.0.1.dist-info/WHEEL
observing_machine-0.0.1.dist-info/top_level.txt
observing_machine-0.0.1.dist-info/RECORD
