Metadata-Version: 2.1
Name: observing-machine
Version: 0.0.1
Summary: Observing Machine
Author-email: Alexander Fedotov <alex.fedotov@aol.com>
Project-URL: Homepage, https://github.com/observing-machine/observing-machine
Project-URL: Bug Tracker, https://github.com/observing-machine/observing-machine/issues
Classifier: Programming Language :: Python :: 3
Classifier: License :: OSI Approved :: MIT License
Classifier: Operating System :: OS Independent
Requires-Python: >=3.10
License-File: LICENSE
